<?xml version="1.0" encoding="UTF-8"?>
<serviceList><service fechaActualizacion="2018-08-01" id="87809"><basicData><language>de</language><name><![CDATA[Barcel&oacute; Imagine]]></name><email>imagine@barcelo.com</email><phone>(+34) 91 732 70 19</phone><fax/><title><![CDATA[Barcel&oacute; Imagine]]></title><body><![CDATA[<p><strong>Das im ehemaligen Foxá 32 untergebrachte Stadthotel der Barceló-Kette liegt im Nordteil des Paseo de la Castellana in der Nähe des Bahnhofs Chamartín. In der 5-Sterne-Unterkunft, die einen perfekten Einklang von Kunst und Technik bietet, ist jeder Winkel der Musik &ndash; vom Rock bis zur Madrider Szene der 70er Jahre - gewidmet.</strong></p><p>Das Hotel verfügt über 156, mit modernster Technik und Komfort ausgestattete Zimmer, in denen Kunst und Musik zur Dekoration gehören. Ebenso vorhanden sind kostenloses WLAN, Sommerpool, Sonnenterrasse, Fitnessraum, Sauna, Parkplatz, Sky Lounge auf dem Dach und ein Gastronomieangebot basierend auf gesunder Ernährung nach dem B-likeat-Konzept. Das Hotel verfügt über mehrere 4-Bett-Zimmer und eignet sich daher bestens für einen Aufenthalt mit der ganzen Familie.</p><p>Weiterhin vorhanden ist ein 249 m2 &nbsp;großer Veranstaltungsraum mit Tageslicht und hochwertiger, moderner Ausstattung, der sich mithilfe von Zwischenwänden in 3 kleinere Räume unterteilen lässt.</p><p>&nbsp;</p>]]></body><web>http://www.esmadrid.com/de/unterkunfte/barcelo-imagine</web></basicData><geoData><address>de Agustín de Foxá, 32</address><zipcode>28036</zipcode><locality/><country>Spain</country><latitude>40.470196157478</latitude><longitude>-3.685238510370</longitude><subAdministrativeArea>Madrid</subAdministrativeArea></geoData><multimedia><media type="image"><description/><url>http://www.esmadrid.com/sites/default/files/recursosturisticos/alojamientos/barcelo_imagine_7.jpg</url></media><media type="image"><description/><url>http://www.esmadrid.com/sites/default/files/recursosturisticos/alojamientos/barcelo_imagine_3.jpg</url></media><media type="image"><description/><url>http://www.esmadrid.com/sites/default/files/recursosturisticos/alojamientos/barcelo_imagine_5.jpg</url></media><media type="image"><description/><url>http://www.esmadrid.com/sites/default/files/recursosturisticos/alojamientos/barcelo_imagine_6.jpg</url></media><media type="image"><description/><url>http://www.esmadrid.com/sites/default/files/recursosturisticos/alojamientos/barcelo_imagine_8.jpg</url></media><media type="image"><description/><url>http://www.esmadrid.com/sites/default/files/recursosturisticos/alojamientos/barcelo_imagine_2.jpg</url></media><media type="image"><description/><url>http://www.esmadrid.com/sites/default/files/recursosturisticos/alojamientos/barcelo_imagine_4.jpg</url></media><media type="image"><description/><url>http://www.esmadrid.com/sites/default/files/recursosturisticos/alojamientos/barcelo_imagine.jpg</url></media></multimedia><extradata><item name="idTipo">3</item><item name="Tipo">Unterkunft</item><categorias><categoria><item name="idCategoria">7022</item><item name="Categoria">Hoteles</item><subcategorias><subcategoria><item name="idSubCategoria">7027</item><item name="SubCategoria">5 estrellas</item></subcategoria></subcategorias></categoria></categorias><item name="Servicios de pago"><![CDATA[]]></item><item name="Horario"><![CDATA[]]></item><fechas/></extradata></service><service fechaActualizacion="2018-04-19" id="87606"><basicData><language>de</language><name><![CDATA[Gran Hotel Ingl&eacute;s]]></name><email>welcome@granhotelingles.com</email><phone>(+34) 91 056 93 84</phone><fax/><title><![CDATA[Gran Hotel Ingl&eacute;s]]></title><body><![CDATA[<p><strong>Das luxuriöse Fünf-Sterne-Hotel der mallorquinischen Kette Hidden Away Hotels, bestehend aus exklusiven Boutique-Hotels, war bei seiner Eröffnung 1886 das erste seiner Art. Und auch das erste Hotel, das ein Restaurant in seinen Räumlichkeiten beherbergte. Heute bietet es nach einer umfassenden Renovierung ein einzigartiges Erlebnis, das den Luxus der goldenen 20er Jahre wieder aufleben lässt.</strong></p><p>Die Art-Déco-Gestaltung des Hotels schafft durch Eleganz, Klasse, Komfort und Raffinesse in Verbindung mit einem sorgfältig ausgearbeiteten Beleuchtungskonzept eine einladende Atmosphäre.</p><p>Das Gebäude verfügt über 48 perfekt schallgedämmte, geräumige Zimmer (alle mit Kingsize-Betten, Bettwäsche aus 500-fädiger ägyptischer Baumwolle, Smart-TV und WLAN), ein großes Fitness-Studio, einen Wellnessbereich, zwei separate Speisesäle und eine Bibliothek namens Salón de las Letras.</p><p>Auch die Gastronomie ist vom Feinsten - Spitzenkoch Willy Moya steht am Herd des Restaurants Lobo 8, dessen Karte sich an die traditionelle Küche anlehnt, und der Lobby-Bar LobByto.</p>]]></body><web>http://www.esmadrid.com/de/unterkunfte/gran-hotel-ingles</web></basicData><geoData><address>Echegaray, 8</address><zipcode>28014</zipcode><locality/><country>Spain</country><latitude>40.415962500000</latitude><longitude>-3.699661000000</longitude><subAdministrativeArea>Madrid</subAdministrativeArea></geoData><multimedia><media type="image"><description/><url>http://www.esmadrid.com/sites/default/files/recursosturisticos/alojamientos/gran_hotel_1.jpg</url></media><media type="image"><description/><url>http://www.esmadrid.com/sites/default/files/recursosturisticos/alojamientos/gran_hotel_2.jpg</url></media><media type="image"><description/><url>http://www.esmadrid.com/sites/default/files/recursosturisticos/alojamientos/pilotohall_granhotelingles.jpg</url></media><media type="image"><description/><url>http://www.esmadrid.com/sites/default/files/recursosturisticos/alojamientos/ghi_habpiloto_1055_high.jpg</url></media><media type="image"><description/><url>http://www.esmadrid.com/sites/default/files/recursosturisticos/alojamientos/ghi_habpiloto_8108_a1_high.jpg</url></media><media type="image"><description/><url>http://www.esmadrid.com/sites/default/files/recursosturisticos/alojamientos/ghi_habpiloto_8128_a1_high.jpg</url></media><media type="image"><description/><url>http://www.esmadrid.com/sites/default/files/recursosturisticos/alojamientos/suite.jpg</url></media></multimedia><extradata><item name="idTipo">3</item><item name="Tipo">Unterkunft</item><categorias><categoria><item name="idCategoria">7022</item><item name="Categoria">Hoteles</item><subcategorias><subcategoria><item name="idSubCategoria">7027</item><item name="SubCategoria">5 estrellas</item></subcategoria></subcategorias></categoria></categorias><item name="Servicios de pago"><![CDATA[]]></item><item name="Horario"><![CDATA[]]></item><fechas/></extradata></service><service fechaActualizacion="2018-09-13" id="87565"><basicData><language>de</language><name><![CDATA[VP Plaza Espa&ntilde;a Design]]></name><email>vp-plaza@vphoteles.com</email><phone>(+34) 91 595 55 10 </phone><fax/><title><![CDATA[VP Plaza Espa&ntilde;a Design]]></title><body><![CDATA[<p><strong>Das 5-Sterne-Haus der Hotelkette VP, das nur wenige Meter von Königspalast, Almudena-Kathedrale und Templo de Debod entfernt liegt, ist dank seiner exklusiven und zeitgemäßen Innenarchitektur das Flaggschiff des Hotelkonzerns. Zu den Highlights des Hotels gehört die Ginkgo Sky Bar in der 12. Etage, die einen unvergleichlichen Blick auf die Stadt bietet.</strong></p><p>Das Hotel verfügt über 214 geräumige Zimmer in 9 verschiedenen Ausführungen, die den unterschiedlichsten Ansprüchen gerecht werden. Hinzu kommen ein eigener Parkplatz, Wellness-Center, Außenpool, Fitnessstudio, das Restaurant Botania (der Firmengruppe Larrumba) und mehr als 1.400 m Quadratmeter Tagungsräume für Veranstaltungen, Kongresse und Meetings aller Art.</p><p>Ganz im Sinne der schwerpunktmäßig künstlerischen Gestaltung der Räumlichkeiten schmücken mehrere Bilder angesehener Künstler die Wände.</p><p>Die Ginkgo Sky Bar ist auch für außenstehende Besucher, die nicht im Hotel logieren, frei zugänglich. Hier bietet sich das ganze Jahr über die Gelegenheit zum Mittagessen, Abendessen und Genuss köstlicher Cocktails vor der Kulisse der Madrider Skyline.</p>]]></body><web>http://www.esmadrid.com/de/unterkunfte/vp-plaza-espana-design</web></basicData><geoData><address>de España, 5</address><zipcode>28008</zipcode><locality/><country>Spain</country><latitude>40.422704185855</latitude><longitude>-3.711751553711</longitude><subAdministrativeArea>Madrid</subAdministrativeArea></geoData><multimedia><media type="image"><description/><url>http://www.esmadrid.com/sites/default/files/recursosturisticos/alojamientos/vp_plaza_espana_design_3.jpg</url></media><media type="image"><description/><url>http://www.esmadrid.com/sites/default/files/recursosturisticos/alojamientos/vp_plaza_espana_design_2.jpg</url></media><media type="image"><description/><url>http://www.esmadrid.com/sites/default/files/recursosturisticos/alojamientos/vp_plaza_espana_design_4.jpg</url></media><media type="image"><description/><url>http://www.esmadrid.com/sites/default/files/recursosturisticos/alojamientos/vp_plaza_espana_design.jpg</url></media><media type="image"><description/><url>http://www.esmadrid.com/sites/default/files/recursosturisticos/alojamientos/vp_plaza_espana_2.jpg</url></media><media type="image"><description/><url>http://www.esmadrid.com/sites/default/files/recursosturisticos/alojamientos/vp_plaza_espana_3.jpg</url></media><media type="image"><description/><url>http://www.esmadrid.com/sites/default/files/recursosturisticos/alojamientos/vp_plaza_espana_5.jpg</url></media><media type="image"><description/><url>http://www.esmadrid.com/sites/default/files/recursosturisticos/alojamientos/vp_plaza_espana_6.jpg</url></media></multimedia><extradata><item name="idTipo">3</item><item name="Tipo">Unterkunft</item><categorias><categoria><item name="idCategoria">7022</item><item name="Categoria">Hoteles</item><subcategorias><subcategoria><item name="idSubCategoria">7027</item><item name="SubCategoria">5 estrellas</item></subcategoria></subcategorias></categoria></categorias><item name="Servicios de pago"><![CDATA[]]></item><item name="Horario"><![CDATA[]]></item><fechas/></extradata></service><service fechaActualizacion="2018-08-01" id="86753"><basicData><language>de</language><name><![CDATA[Hyatt Centric Gran V&iacute;a Madrid]]></name><email>info.centricmadrid@hyatt.com</email><phone>(+34) 918 37 12 34</phone><fax/><title><![CDATA[Hyatt Centric Gran V&iacute;a Madrid]]></title><body><![CDATA[<p><strong>Seit seiner Eröffnung im Dezember 2017 erweitert das Fünf-Sterne-Hotel das umfassende Hotelangebot der Madrider Gran Vía und hat den Anspruch, das Flaggschiff des amerikanischen Unternehmens in Europa zu werden.</strong></p><p>Untergebracht ist das Hotel in einem komplett renovierten zehnstöckigen Jugendstilgebäude aus dem Jahr 1920. Es besitzt 159 Zimmer, davon 16 Suiten mit herrlichem Blick auf die Gran Vía, deren Einrichtung von der Madrider Volkskultur inspiriert wurde. So finden sich etwa &nbsp;spanische Gitarren, Hahnentrittmuster auf Vorhängen und Teppichen sowie Abbildungen von Werken des Madrider Malers Juan Gris.</p><p>Das Hotel bietet mit modernster Technik ausgestattete Tagungsräume, Sportstudio, Food to go, Concierge-Service, mehrsprachiges Personal, Wäscherei und chemische Reinigung.</p><p>Im ersten Stock befindet sich das Restaurant Hielo y Carbón mit einer Kombination aus peruanischer und spanischer Küche, im Erdgeschoss das als Café und Cocktailbar konzipierte Ondas.&nbsp;In der Bar Vía Fantástica auf der Dachterrasse können Sie bei einem Drink schöne Ausblicke auf die Stadt genießen.&nbsp;</p>]]></body><web>http://www.esmadrid.com/de/unterkunfte/hyatt-centric-gran-madrid</web></basicData><geoData><address>Gran Vía, 31</address><zipcode>28013</zipcode><locality/><country>Spain</country><latitude>40.419988600000</latitude><longitude>-3.703756100000</longitude><subAdministrativeArea>Madrid</subAdministrativeArea></geoData><multimedia><media type="image"><description/><url>http://www.esmadrid.com/sites/default/files/recursosturisticos/alojamientos/hyatt_centric_gran_via.jpg</url></media><media type="image"><description/><url>http://www.esmadrid.com/sites/default/files/recursosturisticos/alojamientos/hyatt_centric_gran_via_2.jpg</url></media><media type="image"><description/><url>http://www.esmadrid.com/sites/default/files/recursosturisticos/alojamientos/hyatt_centric_gran_via_4.jpg</url></media><media type="image"><description/><url>http://www.esmadrid.com/sites/default/files/recursosturisticos/alojamientos/hyatt_centric_gran_via_5.jpg</url></media><media type="image"><description/><url>http://www.esmadrid.com/sites/default/files/recursosturisticos/restaurantes/hyatt_centric_gran_via_3.jpg</url></media></multimedia><extradata><item name="idTipo">3</item><item name="Tipo">Unterkunft</item><categorias><categoria><item name="idCategoria">7022</item><item name="Categoria">Hoteles</item><subcategorias><subcategoria><item name="idSubCategoria">7027</item><item name="SubCategoria">5 estrellas</item></subcategoria></subcategorias></categoria></categorias><item name="Servicios de pago"><![CDATA[]]></item><item name="Horario"><![CDATA[]]></item><fechas/></extradata></service><service fechaActualizacion="2017-10-19" id="67861"><basicData><language>de</language><name><![CDATA[Hotel Indigo]]></name><email>info@indigomadrid.com</email><phone>(+34) 91 200 85 85</phone><fax/><title><![CDATA[Hotel Indigo]]></title><body><![CDATA[<p><strong>Das Design dieses Hotels ist von der Gran Vía inspiriert. Eine Straße mit viel Geschichte: Schauplatz zahlreicher Filme, von Protestmärschen und vielfach besungen. Die Wände und Zimmer im Hotel Indigo spiegeln dieses aufregende Leben wider. Die Philosophie des Hotels Indigo lautet: Im Stadtteil, in dem es liegt, leben, arbeiten und Spaß haben. Den lokalen Geschmack in seinen Restaurants genießen und dem Personal, das Sie in mehr als ein Geheimnis des Stadtviertels einweihen wird, vertrauen.</strong></p><p>Das Hotel verfügt über 85 Zimmer in drei unterschiedlichen Kategorien, die sich auf 11 Etagen verteilen: Deluxe, Executive und Suite. Alle Zimmer sind ausgestattet mit eigener Klimaanlage, 40-Zoll-Fernseher, belebenden Brauseregen-Duschen, erstklassigen Pflegeprodukte und WLAN im gesamten Hotel.</p><p>Die Sky Lounge im 12. Stock mit farbenprächtiger Sommerterrasse bietet Cocktailgenuss aus einer umfangreichen Karte und verschiedene Tapas. Im Sommer können Gäste im glasverkleideten Außenpool mit Blick auf die Gran Via baden.&nbsp;</p><p>Das hoteleigene Restaurant El Gato Canalla bietet typische Gerichte der Madrider Küche mit hochwertigen Produkten der Saison.</p>]]></body><web>http://www.esmadrid.com/de/unterkunfte/hotel-indigo</web></basicData><geoData><address>de Silva, 6</address><zipcode>28013</zipcode><locality/><country>Spain</country><latitude>40.420706655201</latitude><longitude>-3.707402944565</longitude><subAdministrativeArea>Madrid</subAdministrativeArea></geoData><multimedia><media type="image"><description/><url>http://www.esmadrid.com/sites/default/files/recursosturisticos/alojamientos/hotelindigo_1400075911.219.jpg</url></media><media type="image"><description/><url>http://www.esmadrid.com/sites/default/files/recursosturisticos/alojamientos/hotel_indigo_madrid_2.jpg</url></media><media type="image"><description/><url>http://www.esmadrid.com/sites/default/files/recursosturisticos/alojamientos/hotel_indigo_madrid_3.jpg</url></media><media type="image"><description/><url>http://www.esmadrid.com/sites/default/files/recursosturisticos/alojamientos/hotel_indigo_madrid_5.jpg</url></media><media type="image"><description/><url>http://www.esmadrid.com/sites/default/files/recursosturisticos/alojamientos/hotel_indigo_madrid.jpg</url></media></multimedia><extradata><item name="idTipo">3</item><item name="Tipo">Unterkunft</item><categorias><categoria><item name="idCategoria">7022</item><item name="Categoria">Hoteles</item><subcategorias><subcategoria><item name="idSubCategoria">7026</item><item name="SubCategoria">4 estrellas</item></subcategoria></subcategorias></categoria></categorias><item name="Servicios de pago"><![CDATA[]]></item><item name="Horario"><![CDATA[]]></item><fechas/></extradata></service><service fechaActualizacion="2018-11-06" id="67801"><basicData><language>de</language><name><![CDATA[Hotel NH Collection Madrid Palacio de Tepa]]></name><email>nhcollectionpalaciodetepa@nh-hotels.com</email><phone>(+34) 91 389 64 90 </phone><fax/><title><![CDATA[Hotel NH Collection Madrid Palacio de Tepa]]></title><body><![CDATA[<p><strong><span>Die Hotelkette NH hat diesen ehemaligen madrilener Palast renoviert, um an der Plaza de Santa Ana, mitten im Viertel Las Letras, ein Luxushotel einzurichten.</span></strong></p><p><span>85 elegant dekorierte Zimmer mit Details spanischer Baukunst aus dem 18. Jahrhundert und Renovierungen, die ihnen modernen Komfort verleihen. Dieses zur Ausnutzung des Tageslichts in hellen Farben minimalistisch dekorierte Hotel bietet Luxus und Komfort in der Nähe der besten Museen der Hauptstadt.</span></p><p>&nbsp;</p>]]></body><web>http://www.esmadrid.com/de/unterkunfte/nh-palacio-de-tepa</web></basicData><geoData><address>San Sebastián , 2</address><zipcode>28012</zipcode><locality/><country>Spain</country><latitude>40.413836800000</latitude><longitude>-3.701579900000</longitude><subAdministrativeArea>Madrid</subAdministrativeArea></geoData><multimedia><media type="image"><description/><url>http://www.esmadrid.com/sites/default/files/recursosturisticos/alojamientos/NHPalaciodeTepa2_1404810310.468.png</url></media><media type="image"><description/><url>http://www.esmadrid.com/sites/default/files/recursosturisticos/alojamientos/NHPalaciodeTepa3_1404810317.044.png</url></media><media type="image"><description/><url>http://www.esmadrid.com/sites/default/files/recursosturisticos/alojamientos/NHPalaciodeTepa5_1404810335.943.png</url></media></multimedia><extradata><item name="idTipo">3</item><item name="Tipo">Unterkunft</item><categorias><categoria><item name="idCategoria">7022</item><item name="Categoria">Hoteles</item><subcategorias><subcategoria><item name="idSubCategoria">7027</item><item name="SubCategoria">5 estrellas</item></subcategoria></subcategorias></categoria></categorias><item name="Servicios de pago"><![CDATA[]]></item><item name="Horario"><![CDATA[]]></item><fechas/></extradata></service><service fechaActualizacion="2018-09-13" id="67755"><basicData><language>de</language><name><![CDATA[The Principal Madrid Hotel]]></name><email>info@theprincipalmadridhotel.com</email><phone>(+34) 91 521 87 43</phone><fax/><title><![CDATA[The Principal Madrid Hotel]]></title><body><![CDATA[<p><strong>Dieses moderne, luxuriöse Boutique-Hotel liegt mitten im Zentrum von Madrid, &nbsp;ganz in der Nähe der Gran Vía und der Calle de Alcalá. Zu den Highlights gehört eine eindrucksvolle Terrasse und ein Ático (Obergeschoss), in dem die Gäste die moderne Haute Cuisine genießen und eine klassische Cocktailbar besuchen können.&nbsp;</strong></p><p>Das Hotel hat 76 elegante, großräumige Zimmer, die mit allem Komfort ausgestattet sind. Im Ático oder der Terrasse, beide mit großzügig begrünten Bereichen, können sich die Gäste an einem Cocktail erfrischen, nach der Karte des namhaften Kochs&nbsp;Ramón Freixa (2 Michelin-Sterne)&nbsp;essen oder sich auf der Sonnenterrasse sonnen und beim Geräusch fallenden Wassers erholen.</p><p>Das Hotel verfügt auch über eine&nbsp;Wellness Suite&nbsp;(mit integrierter Sauna, die exklusiv reserviert werden kann) für Paar- oder Einzelbehandlungen, sowie ein Therapeutenteam für Massagen nach Maß, Personal Trainer-Service, Trainingsraum, Parkplatz und Salons&nbsp; (einige mit Eingang von Gran Vía 2) für Konferenzen, gesellschaftliche Ereignisse oder private Essen.</p><p>&nbsp;</p>]]></body><web>http://www.esmadrid.com/de/unterkunfte/principal-madrid-hotel</web></basicData><geoData><address>Marqués de Valdeiglesias, 1</address><zipcode>28004</zipcode><locality/><country>Spain</country><latitude>40.419357600000</latitude><longitude>-3.697188900000</longitude><subAdministrativeArea>Madrid</subAdministrativeArea></geoData><multimedia><media type="image"><description/><url>http://www.esmadrid.com/sites/default/files/recursosturisticos/alojamientos/prin4_1423149637.318.jpg</url></media><media type="image"><description/><url>http://www.esmadrid.com/sites/default/files/recursosturisticos/alojamientos/prin_1422532073.156.jpg</url></media><media type="image"><description/><url>http://www.esmadrid.com/sites/default/files/recursosturisticos/alojamientos/prin2_1422532088.689.jpg</url></media><media type="image"><description/><url>http://www.esmadrid.com/sites/default/files/recursosturisticos/alojamientos/prin4_1422532094.787.jpg</url></media><media type="image"><description/><url>http://www.esmadrid.com/sites/default/files/recursosturisticos/alojamientos/prin6_1422532103.919.jpg</url></media><media type="image"><description/><url>http://www.esmadrid.com/sites/default/files/recursosturisticos/alojamientos/prin_1423149157.782.jpg</url></media><media type="image"><description/><url>http://www.esmadrid.com/sites/default/files/recursosturisticos/alojamientos/prin2_1423149183.386.jpg</url></media></multimedia><extradata><item name="idTipo">3</item><item name="Tipo">Unterkunft</item><categorias><categoria><item name="idCategoria">7022</item><item name="Categoria">Hoteles</item><subcategorias><subcategoria><item name="idSubCategoria">7027</item><item name="SubCategoria">5 estrellas</item></subcategoria></subcategorias></categoria></categorias><item name="Servicios de pago"><![CDATA[]]></item><item name="Horario"><![CDATA[]]></item><fechas/></extradata></service><service fechaActualizacion="2018-08-01" id="67796"><basicData><language>de</language><name><![CDATA[Hotel &Uacute;nico]]></name><email>info@unicohotelmadrid.com</email><phone>(+34) 91 781 01 73</phone><fax/><title><![CDATA[Hotel &Uacute;nico]]></title><body><![CDATA[<p><strong><span>Dieses Hotel befindet sich in einem typischen madrilenischen Gebäude aus dem 19. Jahrhundert, mit dessen Renovierung Aurelio Rubio beauftragt war. Der historische Wert des Gebäudes wurde beibehalten, allerdings wurde es innovativ gestaltet und mit so viel Komfort ausgestattet, das es zum Vorzeigehotel Madrids aufstieg. Es liegt im kosmopolitischsten und elegantesten Viertel der Hauptstadt Spaniens, dem noblen Stadtviertel Salamanca, umgeben von Luxusboutiquen und nahe beim &bdquo;Dreieck der Kunst&ldquo;: den Museen Prado, Thyssen und Reina Sofía.</span></strong></p><p><span>Die Dekoration des Hotels, für die sich Manolo Melón und dessen Aplomo Team verbürgen, ist etwas ganz Besonderes. Das Ergebnis ist eine perfekte Kombination aus innovativem Design und raffinierter Eleganz, die dieses Hotel zu einer Referenz für Exklusivität in Madrid macht. Jedes Zimmer zeichnet sich durch ein harmonisches Zusammenspiel aus Design und Komfort aus. Alle Zimmer haben Zimmerservice rund um die Uhr, eine individuelle Klimaanlage, Safe in Laptopgröße, Haartrockner, Musikanlage, MP3-Anschluss, DVD und LCD-Flatscreen, interaktiven digitalen Satellitenfernseher sowie kostenlosen WLAN-Internetzugang. Wie jedes Hotel dieser Kategorie hat es eine erstklassige Gastronomie, für die der anerkannte Küchenchef Ramón Freixa, der uns mit innovativen mediterranen Kreationen überrascht, verantwortlich ist.</span></p><p>&nbsp;</p>]]></body><web>http://www.esmadrid.com/de/unterkunfte/hotel-unico</web></basicData><geoData><address>Claudio Coello, 67</address><zipcode>28001</zipcode><locality/><country>Spain</country><latitude>40.428461600000</latitude><longitude>-3.686210800000</longitude><subAdministrativeArea>Madrid</subAdministrativeArea></geoData><multimedia><media type="image"><description/><url>http://www.esmadrid.com/sites/default/files/recursosturisticos/alojamientos/1118819971_2522010123055_adj.jpg</url></media><media type="image"><description/><url>http://www.esmadrid.com/sites/default/files/recursosturisticos/alojamientos/448216819_2522010123035_adj.jpg</url></media><media type="image"><description/><url>http://www.esmadrid.com/sites/default/files/recursosturisticos/alojamientos/252481700_2522010123015_adj.jpg</url></media><media type="image"><description/><url>http://www.esmadrid.com/sites/default/files/recursosturisticos/alojamientos/799458645_2522010123115_adj.jpg</url></media></multimedia><extradata><item name="idTipo">3</item><item name="Tipo">Unterkunft</item><categorias><categoria><item name="idCategoria">7022</item><item name="Categoria">Hoteles</item><subcategorias><subcategoria><item name="idSubCategoria">7027</item><item name="SubCategoria">5 estrellas</item></subcategoria></subcategorias></categoria></categorias><item name="Servicios de pago"><![CDATA[]]></item><item name="Horario"><![CDATA[]]></item><fechas/></extradata></service><service fechaActualizacion="2018-07-30" id="67715"><basicData><language>de</language><name><![CDATA[Villa Magna]]></name><email>villamagna@villamagna.es</email><phone>(+34) 91 587 12 34</phone><fax/><title><![CDATA[Villa Magna]]></title><body><![CDATA[<p><strong>Das Hotel Villa Magna bleibt auch nach einer grundlegenden Renovierung der perfekte Ort für Gäste, die eine ideale Lage im Stadtzentrum suchen. Nur wenige Minuten entfernt befinden sich die besten Museen und die angesehensten Boutiquen der Hauptstadt Spaniens.</strong></p><p>Die 150 weitläufigen Zimmer und Suites vereinen den Charme der restaurierten, antiken Möbel mit dem Stil der neuen Linien in diesem im&nbsp;<strong>Stadtviertel Salamanca</strong> gelegenen Hotel. In den vier exklusiven gastronomischen Bereichen kommen die Gäste den ganzen Tag lang in den Genuss von Gerichten unterschiedlicher gastronomischer Herkunft.</p><p>Das Restaurant Villa Magna bietet eine neue, anregende Küche mit klassischem Touch, die Lounge ist ideal für Frühstück, Mittagessen und zwischendurch, in der Magnum Bar werden originelle Cocktails und leckere Appetithäppchen serviert und das luxuriöse Tse Yang ist auf kanonesische Haute Cuisine spezialisiert.</p><p>Das Hotel verfügt über 800 m&sup2; für Sitzungen und Events: neun kürzlich renovierte Bereiche, fünf Sitzungssäle und La Galeria, ideal für alle Arten von Veranstaltungen, angefangen beim Galadinner, über Cocktailparties bis hin zu Hochzeiten und Pressempfängen.</p>]]></body><web>http://www.esmadrid.com/de/unterkunfte/villa-magna</web></basicData><geoData><address>Castellana, 22</address><zipcode>28046</zipcode><locality/><country>Spain</country><latitude>40.429951500000</latitude><longitude>-3.688152500000</longitude><subAdministrativeArea>Madrid</subAdministrativeArea></geoData><multimedia><media type="image"><description/><url>http://www.esmadrid.com/sites/default/files/recursosturisticos/alojamientos/602378217_29112012123534_adj.jpg</url></media><media type="image"><description/><url>http://www.esmadrid.com/sites/default/files/recursosturisticos/alojamientos/207590783_29112012123743_adj.jpg</url></media><media type="image"><description/><url>http://www.esmadrid.com/sites/default/files/recursosturisticos/alojamientos/1794634814_29112012123450_adj.jpg</url></media><media type="image"><description/><url>http://www.esmadrid.com/sites/default/files/recursosturisticos/alojamientos/668587298_29112012123459_adj.jpg</url></media><media type="image"><description/><url>http://www.esmadrid.com/sites/default/files/recursosturisticos/alojamientos/1881192756_29112012123712_adj.jpg</url></media><media type="image"><description/><url>http://www.esmadrid.com/sites/default/files/recursosturisticos/alojamientos/742012920_29112012123732_adj.jpg</url></media><media type="image"><description/><url>http://www.esmadrid.com/sites/default/files/recursosturisticos/alojamientos/HotelVillaMagna1_1404833054.962.png</url></media></multimedia><extradata><item name="idTipo">3</item><item name="Tipo">Unterkunft</item><categorias><categoria><item name="idCategoria">7022</item><item name="Categoria">Hoteles</item><subcategorias><subcategoria><item name="idSubCategoria">7028</item><item name="SubCategoria">5 estrellas Gran Lujo</item></subcategoria></subcategorias></categoria></categorias><item name="Servicios de pago"><![CDATA[]]></item><item name="Horario"><![CDATA[]]></item><fechas/></extradata></service><service fechaActualizacion="2018-07-30" id="67825"><basicData><language>de</language><name><![CDATA[Eurostars Madrid Tower]]></name><email>reservations@eurostarsmadridtower.com</email><phone>(+34) 91 334 27 00 </phone><fax/><title><![CDATA[Eurostars Madrid Tower]]></title><body><![CDATA[<p><strong><span>Möglicherweise verliert jeder, der aus dem Fenster einer der 474 Zimmer des Eurostars Madrid Tower blickt, die Orientierung. Die KIO Türme, die AZCA Gebäude... Das urbanste Madrid in all seinem Glanz von einem der vier Türme der Business Area aus gesehen- die neue Skyline der Stadt am Paseo de la Castellana.</span></strong></p><p><span>Dieses<span class="apple-converted-space">&nbsp;</span><strong><span>Fünf-Sterne-Hotel</span></strong>, das sich insbesondere an Frauen und Männer auf Geschäftsreise richtet, befindet sich in der 31. bis 50. Etage des 235 Meter hohen<span class="apple-converted-space">&nbsp;</span><strong><span>SACYR Turms</span></strong>-Vallehermoso, Werk der Architekten Enrique Álvarez Sala und Carlos Rubio Carvajal. Seine Dekoration ist so beeindruckend wie seine Silhouette: eine durchgehende, glasbezogene Fassade, die Zimmer überwiegend in Gold- und Metallic-Tönen, die Gemeinschaftsbereiche in Schwarz mit Ausnahme der kühneren Lobby Bar in Grün und Violett.</span></p><p><span>In einigen Zimmern hängen Fotos von anderen Wolkenkratzern auf der Welt, beispielsweise vom Empire State Building in New York und den Petronas Towers in Kuaka Lumpur. Das in der 31. Etage gelegene Restaurant bietet bei Dämmerung einen atemberaubenden Panoramablick. Das Erstaunlichste ist jedoch, sich ein Bad oder einen Saunagang mit direktem Blick auf die Stadt zu gönnen.</span></p><p>&nbsp;</p><p>&nbsp;</p>]]></body><web>http://www.esmadrid.com/de/unterkunfte/eurostars-madrid-tower</web></basicData><geoData><address>de la Castellana, 259 B</address><zipcode>28046</zipcode><locality/><country>Spain</country><latitude>40.476741677704</latitude><longitude>-3.687930107117</longitude><subAdministrativeArea>Madrid</subAdministrativeArea></geoData><multimedia><media type="image"><description/><url>http://www.esmadrid.com/sites/default/files/recursosturisticos/alojamientos/eurostars3.jpg</url></media><media type="image"><description/><url>http://www.esmadrid.com/sites/default/files/recursosturisticos/alojamientos/eurostars.jpg</url></media><media type="image"><description/><url>http://www.esmadrid.com/sites/default/files/recursosturisticos/alojamientos/eurostars4.jpg</url></media><media type="image"><description/><url>http://www.esmadrid.com/sites/default/files/recursosturisticos/alojamientos/eurostars5.jpg</url></media><media type="image"><description/><url>http://www.esmadrid.com/sites/default/files/recursosturisticos/alojamientos/eurostars8.jpg</url></media><media type="image"><description/><url>http://www.esmadrid.com/sites/default/files/recursosturisticos/alojamientos/eurostars6.jpg</url></media></multimedia><extradata><item name="idTipo">3</item><item name="Tipo">Unterkunft</item><categorias><categoria><item name="idCategoria">7022</item><item name="Categoria">Hoteles</item><subcategorias><subcategoria><item name="idSubCategoria">7027</item><item name="SubCategoria">5 estrellas</item></subcategoria></subcategorias></categoria></categorias><item name="Servicios de pago"><![CDATA[]]></item><item name="Horario"><![CDATA[]]></item><fechas/></extradata></service><service fechaActualizacion="2019-04-04" id="67824"><basicData><language>de</language><name><![CDATA[Hilton Madrid Airport]]></name><email>info.madridairport@hilton.com</email><phone>(+34) 91 153 40 00  </phone><fax/><title><![CDATA[Hilton Madrid Airport]]></title><body><![CDATA[<p><strong><span>Die Hotelkette Hilton landet - besser kann man es nicht ausdrücken- mit seinem ersten Hotel wenige Minuten vom internationalen Flughafen Madrid-Barajas. Hilton steht für Eleganz und tadellosen Service und dieses Hotel führt seinen Namen mit allen Konsequenzen.</span></strong></p><p><span>Es bietet King Deluxe, King Guestroom und Twin Guestroom Zimmer, ist zeitgenössisch dekoriert, mit WIFI, Tageslicht, das durch die großen Fenster einfällt, und Marmorbadezimmern. Beeindruckende, 138 Quadratmeter große Presidential-Suite. Mit allen nur erdenklichen und manchmal überraschenden Bequemlichkeiten.</span></p><p><span>Das Hotel richtet sich sowohl an Geschäftsreisende als auch an Familien. Es gibt verschiedene Restaurants: La Plaza zum Frühstücken; Reserva mit raffinierten, mediterranen Gerichten sowie die Ferrum Bar, wo Sie ein Glas Sekt oder einen Cocktail zu kalten Appetithäppchen zu sich nehmen können. Weitere Serviceleistungen: Devisenwechsel, mehrsprachiges Personal, Kürschner, Zimmerservice, Safe u.v.m. Haustiere sind erlaubt.</span></p><p><span>Es gibt nichts Besseres als den Tag mit einem Sonnenbad auf einer der bequemen Liegen und einem Sprung ins Freibad zu beginnen und ausklingen zu lassen, und die Großstadt und den nahe liegenden Flughafens entspannt zu vergessen. Eins der Pools verfügt über Hydrotherapie zur Muskelentspannung und zum Ausruhen in den künstlichen Wellen. Zum Abschluss ein paar Saunagänge oder ein Besuch im Dampfbad.</span></p><p>&nbsp;</p>]]></body><web>http://www.esmadrid.com/de/unterkunfte/hilton-madrid-airport</web></basicData><geoData><address>De la Hispanidad, 2-4</address><zipcode>28042</zipcode><locality/><country>Spain</country><latitude>40.452180440898</latitude><longitude>-3.585748672485</longitude><subAdministrativeArea>Madrid</subAdministrativeArea></geoData><multimedia><media type="image"><description/><url>http://www.esmadrid.com/sites/default/files/recursosturisticos/alojamientos/1979913591_2122008141620_adj.jpg</url></media><media type="image"><description/><url>http://www.esmadrid.com/sites/default/files/recursosturisticos/alojamientos/1521483495_2122008141919_adj.jpg</url></media><media type="image"><description/><url>http://www.esmadrid.com/sites/default/files/recursosturisticos/alojamientos/528768847_2122008141855_adj.jpg</url></media><media type="image"><description/><url>http://www.esmadrid.com/sites/default/files/recursosturisticos/alojamientos/1337818123_212200814209_adj.jpg</url></media><media type="image"><description/><url>http://www.esmadrid.com/sites/default/files/recursosturisticos/alojamientos/136086733_2122008141748_adj.jpg</url></media></multimedia><extradata><item name="idTipo">3</item><item name="Tipo">Unterkunft</item><categorias><categoria><item name="idCategoria">7022</item><item name="Categoria">Hoteles</item><subcategorias><subcategoria><item name="idSubCategoria">7026</item><item name="SubCategoria">4 estrellas</item></subcategoria></subcategorias></categoria></categorias><item name="Servicios de pago"><![CDATA[]]></item><item name="Horario"><![CDATA[]]></item><fechas/></extradata></service><service fechaActualizacion="2018-11-23" id="67763"><basicData><language>de</language><name><![CDATA[Hospes Madrid]]></name><email>madrid@hospes.com</email><phone>(+34) 91 432 29 11</phone><fax/><title><![CDATA[Hotel Hospes Madrid]]></title><body><![CDATA[<p><strong><span>Das im Herbst 2007 eingeweihte Hotel Hospes ist eine Kombination aus eleganten Formen, gehobener Gastronomie und belebender Reinheit im wirtschaftlichen, kulturellen und künstlerischen Zentrum genau gegenüber der Puerta de Alcalá und dem Retiro Park.</span></strong></p><p><span>Das Hotel ist in einem Gebäude eklektischen Stils aus dem Jahr 1883, in dem die Herzogin und Witwe des Generals Prim einst lebte, untergebracht. Die ursprüngliche Gebäudestruktur wurde beibehalten. Im Kontrast dazu steht die moderne und elegante Inneneinrichtung, die sich eindeutig durch die Philosophie und den Stil des Zen auszeichnet, und bei der die Farbe Weiß und Holz die Hauptrolle spielen.</span></p><p><span>Die Gastronomie ist eine der Stärken dieses Hotels, in diesem Sinne bietet das Hotel Hospes das <strong>Restaurante Independencia</strong>. Ein weiterer Trumpf ist das Bodyna Spa &amp; Wellness, ein Bereich zum Entspannen, Ausruhen und sich wohl fühlen voller Licht, Holz und Glas. Hier werden asiatische und westliche Massagen angeboten, Sie können Ihre Spannungen im Fitnesscenter abbauen, sich beim Frisör verwöhnen lassen oder sich im Türkischen Bad entspannen.</span></p><p>&nbsp;</p>]]></body><web>http://www.esmadrid.com/de/unterkunfte/hotel-hospes-madrid</web></basicData><geoData><address>Independencia, 3</address><zipcode>28001</zipcode><locality/><country>Spain</country><latitude>40.420010000000</latitude><longitude>-3.688378000000</longitude><subAdministrativeArea>Madrid</subAdministrativeArea></geoData><multimedia><media type="image"><description/><url>http://www.esmadrid.com/sites/default/files/recursosturisticos/alojamientos/Hospes_Madrid1_alta.jpg</url></media><media type="image"><description/><url>http://www.esmadrid.com/sites/default/files/recursosturisticos/alojamientos/Hospes_Madrid6_alta.jpg</url></media><media type="image"><description/><url>http://www.esmadrid.com/sites/default/files/recursosturisticos/alojamientos/Hospes_Madrid2_alta.jpg</url></media><media type="image"><description/><url>http://www.esmadrid.com/sites/default/files/recursosturisticos/alojamientos/Hospes_Madrid3_alta.jpg</url></media><media type="image"><description/><url>http://www.esmadrid.com/sites/default/files/recursosturisticos/alojamientos/Hospes_Madrid0_alta.jpg</url></media></multimedia><extradata><item name="idTipo">3</item><item name="Tipo">Unterkunft</item><categorias><categoria><item name="idCategoria">7022</item><item name="Categoria">Hoteles</item><subcategorias><subcategoria><item name="idSubCategoria">7027</item><item name="SubCategoria">5 estrellas</item></subcategoria></subcategorias></categoria></categorias><item name="Servicios de pago"><![CDATA[]]></item><item name="Horario"><![CDATA[]]></item><fechas/></extradata></service><service fechaActualizacion="2018-07-18" id="67451"><basicData><language>de</language><name><![CDATA[Petit Palace Posada del Peine]]></name><email>posadadelpeine@petitpalace.com</email><phone>(+34) 91 523 81 51</phone><fax/><title><![CDATA[Petit Palace Posada del Peine]]></title><body><![CDATA[<p><strong>Wahrscheinlich eines der ältesten Hotels Spaniens und das älteste Madrids. Es wurde zu Beginn des 17. Jahrhunderts mit der Absicht gegründet, Gästen und Reisenden, die den Königspalast besuchen wollten, eine Unterkunft zu bieten. Das war naheliegend, da sich dort die Haupthaltestelle der Kutschen befand. Im 19. Jahrhundert wurde das Nebenhaus, das an der Straße Postas in der Nähe der Plaza Mayor lag, in den Hotelkomplex einbezogen, daher der Name und die Größe des Gebäudes.</strong></p><p>Die Lage des Hotelzimmers hing vom Budget der Gäste ab. So waren die Zimmer, die auf die Straße hinausgingen, teurer, aber auch größer, komfortabler und besser belüftet als die, die auf den Innenhof gingen. Nach zahlreichen Umbauten wurde es von der Hotelkette High Tech übernommen, die es im Sommer 2005 unter dem Namen Hotel Petit Palace Posada del Peine wiedereröffnete.</p>]]></body><web>http://www.esmadrid.com/de/unterkunfte/petit-palace-posada-del-peine</web></basicData><geoData><address>Calle Postas, 17, 28012 Madrid, España</address><zipcode>28012</zipcode><locality/><country>Spain</country><latitude>40.415693800000</latitude><longitude>-3.705851400000</longitude><subAdministrativeArea>Madrid</subAdministrativeArea></geoData><multimedia><media type="image"><description/><url>http://www.esmadrid.com/sites/default/files/recursosturisticos/alojamientos/petit_palace_posada_del_peine_0.jpg</url></media><media type="image"><description/><url>http://www.esmadrid.com/sites/default/files/recursosturisticos/alojamientos/PetitPalacePalaciodelPeine2_1404819090.887.png</url></media><media type="image"><description/><url>http://www.esmadrid.com/sites/default/files/recursosturisticos/alojamientos/PetitPalacePalaciodelPeine3_1404819102.385.png</url></media><media type="image"><description/><url>http://www.esmadrid.com/sites/default/files/recursosturisticos/alojamientos/PetitPalacePalaciodelPeine4_1404819188.044.png</url></media></multimedia><extradata><item name="idTipo">3</item><item name="Tipo">Unterkunft</item><categorias><categoria><item name="idCategoria">7022</item><item name="Categoria">Hoteles</item><subcategorias><subcategoria><item name="idSubCategoria">7026</item><item name="SubCategoria">4 estrellas</item></subcategoria></subcategorias></categoria></categorias><item name="Servicios de pago"><![CDATA[]]></item><item name="Horario"><![CDATA[]]></item><fechas/></extradata></service><service fechaActualizacion="2018-11-23" id="67368"><basicData><language>de</language><name><![CDATA[AC Santo Mauro]]></name><email>santo-mauro@ac-hotels.com</email><phone>(+34) 91 319 69 00</phone><fax/><title><![CDATA[AC Santo Mauro]]></title><body><![CDATA[<p><strong>Das Hotel AC Santo Mauro, das in einem majestätischen Gebäude aus dem 19. Jahrhundert untergebracht ist, befindet sich in dem erlesenen Stadtviertel Chamberí, ganz in der Nähe des Paseo de la Castellana. Einer der Juwelen des Hotels ist der tausend Quadratmeter große Garten, in dem wunderschöne Rosen, Eukalyptusbäume und Rosskastanien gedeihen, die dem Hotel einen Pariser Flair im Einklang mit der französisch beeinflussten Innenausstattung verleiht.</strong></p><p>Innen fallen die ehemalige eichengetäfelte Bibliothek auf, die heute als Restaurant dient, sowie die ehemaligen Tanzsäle, die in Sitzungsräume umfunktioniert wurden. In den Hotelzimmern herrscht ein moderner Stil mit viel Glas, Stahl und Wenge-Edelholz vor. Es gibt einen anderen Bereich für Liebhaber von Luxus im alten Stil mit Marmorkamin, alten Stichen und bunten Farben.</p><p>Das Hotel ist komplett rauchfrei.</p>]]></body><web>http://www.esmadrid.com/de/unterkunfte/ac-santo-mauro</web></basicData><geoData><address>Zurbano, 36</address><zipcode>28010</zipcode><locality/><country>Spain</country><latitude>40.431027000000</latitude><longitude>-3.693373900000</longitude><subAdministrativeArea>Madrid</subAdministrativeArea></geoData><multimedia><media type="image"><description/><url>http://www.esmadrid.com/sites/default/files/recursosturisticos/alojamientos/AC_Santo_Mauro3_alta.jpg</url></media><media type="image"><description/><url>http://www.esmadrid.com/sites/default/files/recursosturisticos/alojamientos/AC_Santo_Mauro5_alta.jpg</url></media><media type="image"><description/><url>http://www.esmadrid.com/sites/default/files/recursosturisticos/alojamientos/AC_Santo_Mauro4_alta.jpg</url></media><media type="image"><description/><url>http://www.esmadrid.com/sites/default/files/recursosturisticos/alojamientos/AC_Santo_Mauro6_alta.jpg</url></media><media type="image"><description/><url>http://www.esmadrid.com/sites/default/files/recursosturisticos/alojamientos/AC_Santo_Mauro2_alta.jpg</url></media></multimedia><extradata><item name="idTipo">3</item><item name="Tipo">Unterkunft</item><categorias><categoria><item name="idCategoria">7022</item><item name="Categoria">Hoteles</item><subcategorias><subcategoria><item name="idSubCategoria">7028</item><item name="SubCategoria">5 estrellas Gran Lujo</item></subcategoria></subcategorias></categoria></categorias><item name="Servicios de pago"><![CDATA[]]></item><item name="Horario"><![CDATA[]]></item><fechas/></extradata></service><service fechaActualizacion="2018-11-23" id="67367"><basicData><language>de</language><name><![CDATA[AC Palacio del Retiro]]></name><email>pretiro@ac-hotels.com</email><phone>(+34) 91 523 74 60</phone><fax/><title><![CDATA[AC Palacio del Retiro]]></title><body><![CDATA[<p><strong>Die Hotelkette AC, die stets nach einzigartigen Gebäuden für ihre Hotels in jeder Stadt Ausschau hält, hat einen Palais aus dem beginnenden 20. Jahrhundert, der unter Denkmalschutz steht, in ein Fünf-Sterne-Hotel verwandelt. Das AC Palacio del Retiro</strong><strong>&nbsp;</strong><strong>, das in der Nähe des Retiro-Parks und an dem Straßendreieck zwischen dem Prado Museum, dem Reina Sofía und dem Thyssen Bornemisza liegt, hat außerdem einen großartigen Blick auf den berühmten Park. Aber seine privilegierte Lage in der Hauptstadt ist nicht sein einziger Anziehungspunkt. Der klassische Baustil der Fassade steht im Kontrast zu der avantgardistisch-modernen Innenausstattung. Nach Betreten des Hotels würdigt man eine ausgeglichene Kombination aus kreativen Objekten, die voll im Trend liegen.</strong></p><p>Die Materialien und Bauelemente dieses vierstöckigen Gebäudes - Beton, waagerecht ausgelegte Schmiedestreben und stark bearbeitetes Holz - wurden so gut es ging wieder hergestellt. Lorenzo Marqués, Architekt und mit der Innenausstattung des Hotels beauftragt, bestätigt, dass das Hotel im Allgemeinen auf einen minimalistischen Stil gesetzt hat und dass man den Gegensatz zwischen dem traditionellen Gebäude und dem zeitgenössischen Mobiliar bewusst anstrebte.</p><p>Das Hotel ist komplett rauchfrei.</p>]]></body><web>http://www.esmadrid.com/de/unterkunfte/ac-palacio-del-retiro</web></basicData><geoData><address>Alfonso XII, 14</address><zipcode>28014</zipcode><locality/><country>Spain</country><latitude>40.417786000000</latitude><longitude>-3.688993000000</longitude><subAdministrativeArea>Madrid</subAdministrativeArea></geoData><multimedia><media type="image"><description/><url>http://www.esmadrid.com/sites/default/files/recursosturisticos/alojamientos/AC_Palacio_del_Retiro7_alta.jpg</url></media><media type="image"><description/><url>http://www.esmadrid.com/sites/default/files/recursosturisticos/alojamientos/AC_Palacio_del_Retiro6_alta.jpg</url></media><media type="image"><description/><url>http://www.esmadrid.com/sites/default/files/recursosturisticos/alojamientos/AC_Palacio_del_Retiro8_alta.jpg</url></media><media type="image"><description/><url>http://www.esmadrid.com/sites/default/files/recursosturisticos/alojamientos/PalaciodelRetiro1_1404804672.415.jpg</url></media></multimedia><extradata><item name="idTipo">3</item><item name="Tipo">Unterkunft</item><categorias><categoria><item name="idCategoria">7022</item><item name="Categoria">Hoteles</item><subcategorias><subcategoria><item name="idSubCategoria">7028</item><item name="SubCategoria">5 estrellas Gran Lujo</item></subcategoria></subcategorias></categoria></categorias><item name="Servicios de pago"><![CDATA[]]></item><item name="Horario"><![CDATA[]]></item><fechas/></extradata></service><service fechaActualizacion="2018-07-09" id="67399"><basicData><language>de</language><name><![CDATA[Villa Real]]></name><email>villareal@derbyhotels.com</email><phone>(+34) 91 420 37 67</phone><fax/><title><![CDATA[Villa Real]]></title><body><![CDATA[<p><strong>Vor einigen Jahren kamen kleine, gepflegte Hotels, in denen die Kunden verwöhnt werden, auf. Sie sind der ideale Zufluchtsort nach einem langen Arbeitstag oder Stadtbummel. Das Hotel Villa Real, das neben dem Parlamentsgebäude und nur fünf Minuten von den Museen El Prado, Reina Sofía und Thyssen Bornemisza entfernt liegt, hat seine Vorliebe fürs Klassische nicht eingebüßt. In seinem Innern bewahrt es eine der besten Privatsammlungen mit römischen Mosaiken und Gläsern aus Ampurien aus dem 3. und 4. Jahrhundert n. Chr..</strong></p><p>Das im 19. Jahrhundert errichtete Gebäude wurde mehrmals umgebaut. Der Retiro Park und der Botanische Garten sind einige der Juwelen, die man von der Terrasse aus sieht - zweifelsohne ein privilegierter Blick. Die luxuriösen Zimmer, die mit Möbeln aus dem 19. Jahrhundert, französischen Stoffen und Carrara-Marmor ausgestattet sind, strömen ein warmes, komfortables und diskretes Ambiente aus. Das Hotel verfügt über zwei Restaurants, die in den letzten Jahren mehrere Preise gewonnen haben: Das <strong>East 47</strong>, in dem Sie Autorenküche unter Originalwerken von Andy Warhol zu sich nehmen können, und das&nbsp;<strong>Restaurante Europa</strong> mit internationaler und Marktküche.</p>]]></body><web>http://www.esmadrid.com/de/unterkunfte/villa-real</web></basicData><geoData><address>Plaza de las Cortes, 10 Madrid 28014 España</address><zipcode>28014</zipcode><locality/><country>Spain</country><latitude>40.415527000000</latitude><longitude>-3.696989000000</longitude><subAdministrativeArea>Madrid</subAdministrativeArea></geoData><multimedia><media type="image"><description/><url>http://www.esmadrid.com/sites/default/files/recursosturisticos/alojamientos/villa_real.jpg</url></media><media type="image"><description/><url>http://www.esmadrid.com/sites/default/files/recursosturisticos/alojamientos/villa_real_2.jpg</url></media><media type="image"><description/><url>http://www.esmadrid.com/sites/default/files/recursosturisticos/alojamientos/villa_real_3.jpg</url></media><media type="image"><description/><url>http://www.esmadrid.com/sites/default/files/recursosturisticos/alojamientos/Villa_Real1_alta.jpg</url></media></multimedia><extradata><item name="idTipo">3</item><item name="Tipo">Unterkunft</item><categorias><categoria><item name="idCategoria">7022</item><item name="Categoria">Hoteles</item><subcategorias><subcategoria><item name="idSubCategoria">7027</item><item name="SubCategoria">5 estrellas</item></subcategoria></subcategorias></categoria></categorias><item name="Servicios de pago"><![CDATA[]]></item><item name="Horario"><![CDATA[]]></item><fechas/></extradata></service><service fechaActualizacion="2018-07-09" id="67400"><basicData><language>de</language><name><![CDATA[Hotel Wellington]]></name><email>wellington@hotel-wellington.com</email><phone>(+34) 91 575 44 00 </phone><fax/><title><![CDATA[Wellington]]></title><body><![CDATA[<p><strong>Im Geschäftszentrum des Stadtviertels Salamanca, in dem Luxus und Glamour die Hauptrolle spielen, befindet sich dieses Fünf-Sterne-Hotel. Der Retiro Park, die Puerta de Alcalá und der Paseo del Arte vervollständigen diese exzellente Lage, die allein schon fünf Sterne wert ist.</strong></p><p>Die klassische, aber funktionale Dekoration lädt sowohl in den Zimmern als auch in den restlichen Anlagen zur Entspannung ein. Durch die mit enormen Gemälden zeitgenössischer Kunst geschmückte Eingangshalle gelangt man in die acht Etagen, an denen die modernen Glasfenster mit Stempeldruck auffallen.</p><p>Was die Gastronomie betrifft, so verfügt das Hotel über verschiedene Angebote, je nach Tageszeit und Vorlieben des Gastes. Gerichte à la carte gibt es in den Restaurants&nbsp;<strong>Goizeko Wellington</strong>&nbsp;, das avantgardistische und baskische Haute-Cuisine bietet, und im&nbsp;<strong>Kabuki Wellington</strong>&nbsp;(ein Michelin-Stern) mit dem besten Sushi der Stadt. Ein informelleres Essen oder eine gute Tasse Kaffee genießen Sie am besten im Café&nbsp;<strong>La llave de oro</strong>&nbsp;und einen abendlichen Drink können Sie in der&nbsp;<strong>Bar Inglés</strong> zu sich nehmen. Im Sommer ist ein Sprung ins Pool auf der Dachterrasse mit Blick auf die Puerta de Alcalá bei einem der einzigartigen Sonnenuntergänge Madrids ein wahrer Luxus.</p>]]></body><web>http://www.esmadrid.com/de/unterkunfte/hotel-wellington</web></basicData><geoData><address>Calle de Velázquez, 8, 28001 Madrid</address><zipcode>28001</zipcode><locality/><country>Spain</country><latitude>40.422040000000</latitude><longitude>-3.684210000000</longitude><subAdministrativeArea>Madrid</subAdministrativeArea></geoData><multimedia><media type="image"><description/><url>http://www.esmadrid.com/sites/default/files/recursosturisticos/alojamientos/hotel_wellington.jpg</url></media><media type="image"><description/><url>http://www.esmadrid.com/sites/default/files/recursosturisticos/alojamientos/HotelWellingtonPiscina_1412173243.425.jpg</url></media><media type="image"><description/><url>http://www.esmadrid.com/sites/default/files/recursosturisticos/alojamientos/hotel_wellington_3.jpg</url></media><media type="image"><description/><url>http://www.esmadrid.com/sites/default/files/recursosturisticos/alojamientos/hotel_wellington_2.jpg</url></media><media type="image"><description/><url>http://www.esmadrid.com/sites/default/files/recursosturisticos/alojamientos/HotelWellingtonTerraza_1412173225.635.jpg</url></media><media type="image"><description/><url>http://www.esmadrid.com/sites/default/files/recursosturisticos/alojamientos/HotelWellingtonFachada_1412173215.885.jpg</url></media></multimedia><extradata><item name="idTipo">3</item><item name="Tipo">Unterkunft</item><categorias><categoria><item name="idCategoria">7022</item><item name="Categoria">Hoteles</item><subcategorias><subcategoria><item name="idSubCategoria">7027</item><item name="SubCategoria">5 estrellas</item></subcategoria></subcategorias></categoria></categorias><item name="Servicios de pago"><![CDATA[]]></item><item name="Horario"><![CDATA[]]></item><fechas/></extradata></service><service fechaActualizacion="2018-07-09" id="67370"><basicData><language>de</language><name><![CDATA[Gran Meli&aacute; F&eacute;nix]]></name><email>gran.melia.fenix@melia.com</email><phone>(+34) 91 431 67 00</phone><fax/><title><![CDATA[Hotel Gran Meli&aacute; F&eacute;nix]]></title><body><![CDATA[<p><strong><span>Das Hotel Gran Meliá Fénix, das sich direkt an der Plaza de Colón, im Herzen des Finanzzentrums der Stadt und in der Nähe der Straßen Goya, Paseo de la Castellana und Serrano befindet, ist eines der großen Luxushotels der Hauptstadt Spaniens. Aufgrund seiner Lage ist es die ideale Unterkunft für Freizeit- und Geschäftsreisende sowie für diejenigen, die Madrid auf der Suche nach exklusiver Mode besuchen.</span></strong></p><p><span>Das im September 1953 eingeweihte und 2001 völlig renovierte Gran Meliá Fénix hat von außen einen neoklassischen Baustil, während es in den Innenräumen eine höfische Dekoration im Einklang mit seiner Umgebung aufrecht erhalten hat.</span></p><p><span>Viele prominente Persönlichkeiten sind in diesem Hotel untergekommen: Gregory Peck, der der Eröffnungsfeier beiwohnte, Gloria Swanson, Rita Hayworth, Cary Grant und Charles Bronson, die die klassische Dekoration und den aristokratischen Glanz dieses Hotels ausströmte, liebten. Am stärksten in der Erinnerung verhaftet blieb allerdings der Besuch der Beatles, die sich 1965 bei ihrem einzigen Konzert, das sie in Madrid gaben, für das Gran Meliá Fénix entschieden.</span></p><p>&nbsp;</p>]]></body><web>http://www.esmadrid.com/de/unterkunfte/gran-melia-fenix</web></basicData><geoData><address>Calle de Hermosilla 2 Madrid</address><zipcode>28001</zipcode><locality/><country>Spain</country><latitude>40.426598000000</latitude><longitude>-3.689256000000</longitude><subAdministrativeArea>Madrid</subAdministrativeArea></geoData><multimedia><media type="image"><description/><url>http://www.esmadrid.com/sites/default/files/recursosturisticos/alojamientos/gran_melia_fenix.jpg</url></media><media type="image"><description/><url>http://www.esmadrid.com/sites/default/files/recursosturisticos/alojamientos/gran_melia_fenix_0.jpg</url></media><media type="image"><description/><url>http://www.esmadrid.com/sites/default/files/recursosturisticos/alojamientos/gran_melia_fenix_3.jpg</url></media><media type="image"><description/><url>http://www.esmadrid.com/sites/default/files/recursosturisticos/alojamientos/gran_melia_fenix_2_0.jpg</url></media></multimedia><extradata><item name="idTipo">3</item><item name="Tipo">Unterkunft</item><categorias><categoria><item name="idCategoria">7022</item><item name="Categoria">Hoteles</item><subcategorias><subcategoria><item name="idSubCategoria">7028</item><item name="SubCategoria">5 estrellas Gran Lujo</item></subcategoria></subcategorias></categoria></categorias><item name="Servicios de pago"><![CDATA[]]></item><item name="Horario"><![CDATA[]]></item><fechas/></extradata></service><service fechaActualizacion="2018-07-09" id="67371"><basicData><language>de</language><name><![CDATA[Hesperia Madrid]]></name><email>hotel@hesperia-madrid.com</email><phone>(+34) 91 210 88 00</phone><fax/><title><![CDATA[Hotel Hesperia Madrid]]></title><body><![CDATA[<p><strong><span>Das direkt am Paseo de la Castellana gelegene Hotel Hesperia ist wegen seiner guten Anbindung an den Flughafen Barajas, das Messegelände von Madrid und das größte Geschäftsviertel der Stadt für Manager besonders empfehlenswert.</span></strong></p><p><span>Seine klassisch-moderne Dekoration von Pascua Ortega und die Grandezza seiner Zimmer machen es zu einem der großartigen Hotels der Hauptstadt Spaniens. Es gibt Zimmerservice rund um die Uhr sowie Essensservice, damit unsere Gäste sich zu Hause fühlen.</span></p><p><span>Was die Restaurants betrifft, so ist für jeden Geschmack etwas dabei. Das Restaurant La Manzana bietet eine Karte mit typisch mediterranen Gerichten und das Restaurant Santceloni, das von Óscar Velasco geführt wird, ist für die Haute Cuisine zuständig.</span></p><p>&nbsp;</p>]]></body><web>http://www.esmadrid.com/de/unterkunfte/hotel-hesperia-madrid</web></basicData><geoData><address>Paseo de la Castellana, 57 28046 Madrid</address><zipcode>28046</zipcode><locality/><country>Spain</country><latitude>40.438770000000</latitude><longitude>-3.691349000000</longitude><subAdministrativeArea>Madrid</subAdministrativeArea></geoData><multimedia><media type="image"><description/><url>http://www.esmadrid.com/sites/default/files/recursosturisticos/alojamientos/hesperia_madrid_3.jpg</url></media><media type="image"><description/><url>http://www.esmadrid.com/sites/default/files/recursosturisticos/alojamientos/hesperia_madrid.jpg</url></media><media type="image"><description/><url>http://www.esmadrid.com/sites/default/files/recursosturisticos/alojamientos/hesperia_madrid_2.jpg</url></media><media type="image"><description/><url>http://www.esmadrid.com/sites/default/files/recursosturisticos/alojamientos/hesperiamadrid2_1415015881.867.png</url></media></multimedia><extradata><item name="idTipo">3</item><item name="Tipo">Unterkunft</item><categorias><categoria><item name="idCategoria">7022</item><item name="Categoria">Hoteles</item><subcategorias><subcategoria><item name="idSubCategoria">7027</item><item name="SubCategoria">5 estrellas</item></subcategoria></subcategorias></categoria></categorias><item name="Servicios de pago"><![CDATA[]]></item><item name="Horario"><![CDATA[]]></item><fechas/></extradata></service><service fechaActualizacion="2018-07-06" id="67389"><basicData><language>de</language><name><![CDATA[InterContinental Madrid]]></name><email>icmadrid@ihg.com</email><phone>(+34)  900 983 177</phone><fax/><title><![CDATA[InterContinental Madrid]]></title><body><![CDATA[<p><strong><span>Das InterContinental Madrid, das als eines der besten Hotels für Geschäftsreisen in der Hauptstadt Spaniens bekannt ist, ist exklusiv mit allem ausgestattet, was ein Luxushotel Geschäftsreisenden in Madrid bieten kann. Dank seiner Lage ganz in der Nähe der großen Museen, dem Stadtzentrum und dem Fußballstadion Santiago Bernabéu ist es auch eine gute Wahl für diejenigen, die Kultur und Freizeit in Madrid genießen möchten.</span></strong></p><p><span>Das Gebäude ging Mitte des letzten Jahrhunderts aus einem Palais aus dem 18. Jahrhundert hervor und liegt direkt am<span class="apple-converted-space">&nbsp;</span><strong><span>Paseo de la Castellana</span></strong><span class="apple-converted-space">&nbsp;</span>. Es hat sich stets von der exquisiten künstlerischen Tradition Madrids inspirieren lassen. Mit der Zeit hat es neue Technologien eingeführt und sich auf Geschäftsreisende spezialisiert, für die der exklusive Sala Club InterContinental sowie 17 Sitzungssäle, alle mit Tageslicht, eingerichtet wurden.</span></p><p><span>Auch die Gastronomie ist eine Stärke des Hotels. Die auf Cocktails und leichte Appetithäppchen spezialisierte Bar 49 eignet sich eher für informelle Anlässe. Denjenigen, die lieber à la carte essen, bietet der Küchenchef José Luque im Restaurant El Jardín del InterContinental eine sorgfältig zubereitete spanische Küche, die Sie im Sommer auch auf der Terrasse des Hotels zu sich nehmen können. Sonntags gibt es einen umwerfenden Brunch.</span></p><p>&nbsp;</p>]]></body><web>http://www.esmadrid.com/de/unterkunfte/intercontinental-madrid</web></basicData><geoData><address>Paseo De La Castellana 49 : Madrid ,28046, Spain</address><zipcode>28046</zipcode><locality/><country>Spain</country><latitude>40.436333000000</latitude><longitude>-3.690009000000</longitude><subAdministrativeArea>Madrid</subAdministrativeArea></geoData><multimedia><media type="image"><description/><url>http://www.esmadrid.com/sites/default/files/recursosturisticos/alojamientos/intercontinental_madrid.jpg</url></media><media type="image"><description/><url>http://www.esmadrid.com/sites/default/files/recursosturisticos/alojamientos/Intercontinental4_1404807632.178.jpg</url></media><media type="image"><description/><url>http://www.esmadrid.com/sites/default/files/recursosturisticos/alojamientos/intercontinental_madrid_2.jpg</url></media><media type="image"><description/><url>http://www.esmadrid.com/sites/default/files/recursosturisticos/alojamientos/intercontinental_madrid_3_0.jpg</url></media><media type="image"><description/><url>http://www.esmadrid.com/sites/default/files/recursosturisticos/alojamientos/Intercontinental2_1404807548.478.jpg</url></media></multimedia><extradata><item name="idTipo">3</item><item name="Tipo">Unterkunft</item><categorias><categoria><item name="idCategoria">7022</item><item name="Categoria">Hoteles</item><subcategorias><subcategoria><item name="idSubCategoria">7027</item><item name="SubCategoria">5 estrellas</item></subcategoria></subcategorias></categoria></categorias><item name="Servicios de pago"><![CDATA[]]></item><item name="Horario"><![CDATA[]]></item><fechas/></extradata></service><service fechaActualizacion="2018-07-06" id="67392"><basicData><language>de</language><name><![CDATA[Eurostars Suites Mirasierra]]></name><email>info@eurostarssuitesmirasierra.com</email><phone>(+34) 913 342 196</phone><fax/><title><![CDATA[Eurostars Suites Mirasierra]]></title><body><![CDATA[<p><strong>Eurostars Suites Mirasierra befindet sich in einem Wohnviertel in der Nähe des Finanzzentrums Cuatro Torres, dem Paseo de la Castellana und dem Bahnhof Chamartín, und es ist ca. 15 Minuten vom Flughafen Madrid-Barajas und der Messe von Madrid (IFEMA) entfernt.</strong></p><p>Gehört heute zu den Einrichtungen der Stadt mit den besten Voraussetzungen für Firmentagungen, Events und Feiern, dank 17 separater Veranstaltungsräume mit über 1.800 m2 Fläche und Platz für bis zu 850 Personen. Die meisten der 182 Zimmer der Anlage bieten einen herrlichen Blick auf die Berge um Madrid. Alle Suiten des Hotels sind mindestens 60 m2 groß und sorgen so mit ihrem größzügigen Ambiente für die vollkommene Entspannung unserer Gäste.&nbsp;</p><p>Zur perfekten Ausstattung des Eurostars Suites Mirasierra gehört ein ausgezeichneter Restaurantservice, der sowohl im Restaurant als auch in der Lobby-Bar mit einem exquisiten und abwechslungsreichen kulinarischen Angebot aufwartet. Den Hotelgästen steht während der Saison ein fantastischer Pool mit Terrasse und Bar zur Verfügung - eine ideale Möglichkeit, alle Annehmlichkeiten des Hotels unter freiem Himmel zu genießen.</p>]]></body><web>http://www.esmadrid.com/de/unterkunfte/eurostars-suites-mirasierra</web></basicData><geoData><address>Alfredo Marqueríe, 43 Madrid 28034 España</address><zipcode>28034</zipcode><locality/><country>Spain</country><latitude>40.486518000000</latitude><longitude>-3.703443400000</longitude><subAdministrativeArea>Madrid</subAdministrativeArea></geoData><multimedia><media type="image"><description/><url>http://www.esmadrid.com/sites/default/files/recursosturisticos/alojamientos/SheratonMadridMirasierra5_1404822031.014.png</url></media><media type="image"><description/><url>http://www.esmadrid.com/sites/default/files/recursosturisticos/alojamientos/eurostar_hotel_mirasierra_1.jpg</url></media><media type="image"><description/><url>http://www.esmadrid.com/sites/default/files/recursosturisticos/alojamientos/SheratonMadridMirasierra3_1404822007.487.png</url></media><media type="image"><description/><url>http://www.esmadrid.com/sites/default/files/recursosturisticos/alojamientos/SheratonMadridMirasierra4_1404822016.508.png</url></media><media type="image"><description/><url>http://www.esmadrid.com/sites/default/files/recursosturisticos/alojamientos/eurostars_suites_mirasierra_2_0.jpg</url></media></multimedia><extradata><item name="idTipo">3</item><item name="Tipo">Unterkunft</item><categorias><categoria><item name="idCategoria">7022</item><item name="Categoria">Hoteles</item><subcategorias><subcategoria><item name="idSubCategoria">7027</item><item name="SubCategoria">5 estrellas</item></subcategoria></subcategorias></categoria></categorias><item name="Servicios de pago"><![CDATA[]]></item><item name="Horario"><![CDATA[]]></item><fechas/></extradata></service><service fechaActualizacion="2018-09-13" id="67393"><basicData><language>de</language><name><![CDATA[Hotel Miguel &Aacute;ngel]]></name><email>reservas.miguelangel@grupobluebay.com</email><phone> (+34) 91 442 00 22 </phone><fax/><title><![CDATA[Hotel Occidental Miguel &Aacute;ngel]]></title><body><![CDATA[<p><strong><span>Das Hotel Occidental Miguel Ángel hat dank der wertvollen Kunstwerke, die es schmücken, ein klassisches Ambiente. Das 1977 von Königin Sofia, damals noch Prinzessin von Asturien, eingeweihte Hotel befindet sich in privilegierter Lage nahe des Geschäftszentrums von Madrid und der Luxusboutiquen des Stadtviertels Salamanca. Als Vorreiter für exklusive Serviceleistungen für spezielle Gäste verfügt es über ein großes Spa mit Hydrotherapie mit klimatisiertem Innenpool, Whirlpool, finnischer Sauna, türkischem Bad und Dusche mit Essenzen.</span></strong></p><p><span>Für eine Unterkunft im Hotel Occidental Miguel Ángel entschieden sich bekannte Schauspieler wie Jeremy Irons und Ewan McGregor sowie Künstler wie Plácido Domingo, Peter Gabriel und Cher. Im Gedächtnis ist insbesondere der Literaturnobelpreisträger Camilo José Cela, der sich jede Woche im Hotel einmietete, haften geblieben.</span></p><p><span>Der Aufenthalt des ehemaligen Präsidenten der U.S.A., Bill Clinton, ist eine weitere Anekdote des Hotels. Zusammen mit seiner Familie besuchte er 1997 fünf Tage lang Spanien. Das Hotel, das mit der Delegation des damaligen Präsidenten der U.S.A. völlig ausgebucht war, verwandelte sich in den sichersten Ort der Welt. Zum Wohlergehen der Familie Clinton wurde ihr eine maßgeschneiderte Suite hergerichtet. Eins der Zimmer wurde zum Ankleideraum, der ausschließlich von Frau Clinton und deren persönlicher Kosmetikerin genutzt wurde. Außerdem brachte die Familie ihren persönlichen Butler mit, der sich in der Küche niederließ und alle Gerichte kostete, bevor sie der Familie Clinton serviert wurden.</span></p><p>&nbsp;</p>]]></body><web>http://www.esmadrid.com/de/unterkunfte/hotel-occidental-miguel-angel</web></basicData><geoData><address>Miguel Ángel, 29-31</address><zipcode>28010</zipcode><locality/><country>Spain</country><latitude>40.437380000000</latitude><longitude>-3.691250000000</longitude><subAdministrativeArea>Madrid</subAdministrativeArea></geoData><multimedia><media type="image"><description/><url>http://www.esmadrid.com/sites/default/files/recursosturisticos/alojamientos/Occidental_Miguel_Angel4_alta.jpg</url></media><media type="image"><description/><url>http://www.esmadrid.com/sites/default/files/recursosturisticos/alojamientos/Occidental_Miguel_Angel6_alta.jpg</url></media><media type="image"><description/><url>http://www.esmadrid.com/sites/default/files/recursosturisticos/alojamientos/exteriorMA_1402070373.388.jpg</url></media><media type="image"><description/><url>http://www.esmadrid.com/sites/default/files/recursosturisticos/alojamientos/hotel_miguel_angel.jpg</url></media><media type="image"><description/><url>http://www.esmadrid.com/sites/default/files/recursosturisticos/alojamientos/hotel_miguel_angel_2.jpg</url></media><media type="image"><description/><url>http://www.esmadrid.com/sites/default/files/recursosturisticos/alojamientos/hotel_miguel_angel_3.jpg</url></media></multimedia><extradata><item name="idTipo">3</item><item name="Tipo">Unterkunft</item><categorias><categoria><item name="idCategoria">7022</item><item name="Categoria">Hoteles</item><subcategorias><subcategoria><item name="idSubCategoria">7027</item><item name="SubCategoria">5 estrellas</item></subcategoria></subcategorias></categoria></categorias><item name="Servicios de pago"><![CDATA[]]></item><item name="Horario"><![CDATA[]]></item><fechas/></extradata></service><service fechaActualizacion="2018-07-10" id="67394"><basicData><language>de</language><name><![CDATA[Orfila]]></name><email>inforeservas@hotelorfila.com</email><phone>(+34) 91 702 77 70</phone><fax/><title><![CDATA[Orfila]]></title><body><![CDATA[<p><strong><span>Das Orfila ist ein Hotel, das Sie in eine andere Zeit befördert, sobald Sie es betreten haben. Schon von außen lässt sich erahnen, was sich im Innern verbirgt, denn es ist in einem Palais aus dem 19. Jahrhundert untergebracht, der in einem der charmantesten Viertel der Stadt - Chamberí-&nbsp; an der Straße, nach dem es benannt ist, liegt.</span></strong></p><p><span>Drinnen bestätigen die Freitreppe und die Halle, die in ihrem ursprünglichen Zustand erhalten sind, die Wandbehänge, die antiken Möbel und im Allgemeinen der im Hotel vorherrschende klassische Stil die anfänglichen Vermutungen. Jedes Hotelzimmer ist einzigartig, jedes hat einen anderen Baustil und die Dekoration unterscheidet sich von der der anderen Zimmer. Aber allen ist etwas gemein: Sie transportieren Sie ins 19. Jahrhundert, allerdings mit den Bequemlichkeiten, die nur die modernsten Hotels bieten.</span></p><p><span>Auch der Rest des Hotels ist von diesem Palaisstil durchtränkt. Der Teesalon, der Sitzungssaal, die Bar im englischen Stil und das Restaurant El Jardín de Orfila vervollständigen das Angebot für einen Luxusaufenthalt in einer anderen Epoche. Vielleicht ist dies der Grund, warum das Hotel Orfila sich als einziges in Madrid in die Kette Relais &amp; Châteaux,, die einige der angesehensten kleinen Hotels der Welt aufnimmt und der weltweit etwas mehr als 400 Hotels, davon zwanzig spanische, angehören, hineinschmuggeln konnte.</span></p><p>&nbsp;</p>]]></body><web>http://www.esmadrid.com/de/unterkunfte/orfila</web></basicData><geoData><address>Calle de Orfila, 6, 28010 Madrid</address><zipcode>28010</zipcode><locality/><country>Spain</country><latitude>40.427376000000</latitude><longitude>-3.693035000000</longitude><subAdministrativeArea>Madrid</subAdministrativeArea></geoData><multimedia><media type="image"><description/><url>http://www.esmadrid.com/sites/default/files/recursosturisticos/alojamientos/orfila_3.jpg</url></media><media type="image"><description/><url>http://www.esmadrid.com/sites/default/files/recursosturisticos/alojamientos/orfila_2.jpg</url></media><media type="image"><description/><url>http://www.esmadrid.com/sites/default/files/recursosturisticos/alojamientos/orfila.jpg</url></media><media type="image"><description/><url>http://www.esmadrid.com/sites/default/files/recursosturisticos/alojamientos/orfila_0.jpg</url></media><media type="image"><description/><url>http://www.esmadrid.com/sites/default/files/recursosturisticos/alojamientos/orfila6.jpg</url></media></multimedia><extradata><item name="idTipo">3</item><item name="Tipo">Unterkunft</item><categorias><categoria><item name="idCategoria">7022</item><item name="Categoria">Hoteles</item><subcategorias><subcategoria><item name="idSubCategoria">7027</item><item name="SubCategoria">5 estrellas</item></subcategoria></subcategorias></categoria></categorias><item name="Servicios de pago"><![CDATA[]]></item><item name="Horario"><![CDATA[]]></item><fechas/></extradata></service><service fechaActualizacion="2018-08-27" id="67395"><basicData><language>de</language><name><![CDATA[Puerta Am&eacute;rica]]></name><email>hotel.puertamerica@hoteles-silken.com</email><phone>(+34) 91 744 54 00</phone><fax/><title><![CDATA[Puerta Am&eacute;rica]]></title><body><![CDATA[<p><strong>Das Hotel Puerta de América ist nicht nur ein großartiges Luxushotel und ein Symbol der Modernität, es ist darüber hinaus ein Treffpunkt verschiedener Kulturen und Sichtweisen von Architektur und Design.</strong></p><p>An dem 2006 eingeweihten Bauwerk waren neunzehn der besten Architektur- und Designerstudios aus dreizehn verschiedenen Ländern beteiligt, die mit unterschiedlichen Materialien, Farben und Formen spielten, um verschiedene Räume zu erschaffen, die das beste aus der Welt der Architektur und des Avantgardedesigns, bei dem sie ihrer Kreativität freien Lauf lassen konnten, in sich vereinen.</p><p>Die ursprüngliche Idee war, unterschiedliche Perspektiven von Architektur, Design und der Kunst miteinander zu verbinden. Zu diesem Zweck arbeitete man mit Persönlichkeiten wie Jean Nouvel, der für die letzte Etage der aufsehenerregenden Fassade zuständig war, Javier Mariscal, Fernando Salas, Richard Gluckman, Victorio &amp; Lucchino, Norman Foster, Zaha Hadid und anderen. Das Ergebnis ist Originalität, Luxus, Innovation und formale Freiheit bei einem eminent eklektischen Hotel, in dem der Gast bei jedem Besuch ein neues kreatives Universum entdecken kann.</p>]]></body><web>http://www.esmadrid.com/de/unterkunfte/puerta-america</web></basicData><geoData><address>América, 41</address><zipcode>28002</zipcode><locality/><country>Spain</country><latitude>40.440254000000</latitude><longitude>-3.670216000000</longitude><subAdministrativeArea>Madrid</subAdministrativeArea></geoData><multimedia><media type="image"><description/><url>http://www.esmadrid.com/sites/default/files/recursosturisticos/alojamientos/SilkenPuertadeAmerica1_1404822681.366.png</url></media><media type="image"><description/><url>http://www.esmadrid.com/sites/default/files/recursosturisticos/alojamientos/Silken_Puerta_de_America16_alta.jpg</url></media><media type="image"><description/><url>http://www.esmadrid.com/sites/default/files/recursosturisticos/alojamientos/Silken_Puerta_de_America5_alta.jpg</url></media><media type="image"><description/><url>http://www.esmadrid.com/sites/default/files/recursosturisticos/alojamientos/Silken_Puerta_de_America8_alta.jpg</url></media><media type="image"><description/><url>http://www.esmadrid.com/sites/default/files/recursosturisticos/alojamientos/Silken_Puerta_de_America9_alta.jpg</url></media><media type="image"><description/><url>http://www.esmadrid.com/sites/default/files/recursosturisticos/alojamientos/Silken_Puerta_de_America13_alta.jpg</url></media><media type="image"><description/><url>http://www.esmadrid.com/sites/default/files/recursosturisticos/alojamientos/Silken_Puerta_de_America17_alta.jpg</url></media></multimedia><extradata><item name="idTipo">3</item><item name="Tipo">Unterkunft</item><categorias><categoria><item name="idCategoria">7022</item><item name="Categoria">Hoteles</item><subcategorias><subcategoria><item name="idSubCategoria">7028</item><item name="SubCategoria">5 estrellas Gran Lujo</item></subcategoria></subcategorias></categoria></categorias><item name="Servicios de pago"><![CDATA[]]></item><item name="Horario"><![CDATA[]]></item><fechas/></extradata></service><service fechaActualizacion="2018-11-23" id="67396"><basicData><language>de</language><name><![CDATA[Ritz Madrid]]></name><email>rzmad-reservations@mohg.com</email><phone>(+34) 91 701 67 67</phone><fax/><title><![CDATA[Ritz Madrid]]></title><body><![CDATA[<p><strong>Das Hotel Ritz, das Lieblingshotel des europäischen Adels, wurde von Alfons XIII und Victoria Eugenia de Battenberg am 2. Oktober 1910 eingeweiht. Das Hotel entsprang der Notwendigkeit, dem Adel und anderen prominenten Persönlichkeiten vergangener Zeiten eine Unterkunft zu bieten. Noch heute, fast hundert Jahre später, empfängt es bedeutende Personen aus Kultur, Politik und Kunst an seiner hervorragenden Lage mitten im &bdquo;Dreieick der Kunst&ldquo;.</strong></p><p>Zu den Königshäusern, die hier gewohnt haben, zählen der Maharadscha von Kapurtala und seine Gattin, Prinz Charles von England und Lady Di sowie der Herzog von Windsor und dessen Frau. Auch die Liste der Hollywood-Stars ist lang: Henry Fonda, Cary Grant, Orson Welles, Rita Hayworth, Sofia Loren, Elisabeth Taylor, Richard Gere, Warren Beatty, Mel Gibson, Jodie Foster und Julia Roberts sind nur einige der Gäste dieses hundertjährigen Hotels.</p><p>In der Erinnerung geblieben sind auch die zwanzig Jahre, in denen die Schauspielerin Ava Gardner dieses Hotel für ihre Aufenthalte in Madrid auswählte sowie der Besuch von Frank Sinatra. Aber wenn jemand hervorgehoben werden sollte, dann ist es Linda Fiorentino, Femme Fatale des amerikanischen Films, die gelegentlich im Ritz unterkam. Die Schauspielerin betont, dass jedes Mal, wenn sie ins Hotel kommt, könne sie vor Aufregung beim Anblick des Prado Museums und der Apollo-Statue vor dem Eingang kein Auge schließen.</p>]]></body><web>http://www.esmadrid.com/de/unterkunfte/ritz-madrid</web></basicData><geoData><address>de la Lealtad, 5</address><zipcode>28014</zipcode><locality/><country>Spain</country><latitude>40.415833000000</latitude><longitude>-3.693413000000</longitude><subAdministrativeArea>Madrid</subAdministrativeArea></geoData><multimedia><media type="image"><description/><url>http://www.esmadrid.com/sites/default/files/recursosturisticos/alojamientos/Ritz14_alta.jpg</url></media><media type="image"><description/><url>http://www.esmadrid.com/sites/default/files/recursosturisticos/alojamientos/Ritz22_alta.jpg</url></media><media type="image"><description/><url>http://www.esmadrid.com/sites/default/files/recursosturisticos/alojamientos/HotelRitz1_1404820440.621.png</url></media><media type="image"><description/><url>http://www.esmadrid.com/sites/default/files/recursosturisticos/alojamientos/HotelRitz2_1404820455.633.png</url></media><media type="image"><description/><url>http://www.esmadrid.com/sites/default/files/recursosturisticos/alojamientos/HotelRitz3_1404820401.219.png</url></media><media type="image"><description/><url>http://www.esmadrid.com/sites/default/files/recursosturisticos/alojamientos/HotelRitz4_1404820479.772.png</url></media><media type="image"><description/><url>http://www.esmadrid.com/sites/default/files/recursosturisticos/alojamientos/HotelRitz5_1404820507.322.png</url></media><media type="image"><description/><url>http://www.esmadrid.com/sites/default/files/recursosturisticos/alojamientos/HotelRitz7_1404820518.26.png</url></media></multimedia><extradata><item name="idTipo">3</item><item name="Tipo">Unterkunft</item><categorias><categoria><item name="idCategoria">7022</item><item name="Categoria">Hoteles</item><subcategorias><subcategoria><item name="idSubCategoria">7028</item><item name="SubCategoria">5 estrellas Gran Lujo</item></subcategoria></subcategorias></categoria></categorias><item name="Servicios de pago"><![CDATA[]]></item><item name="Horario"><![CDATA[]]></item><fechas/></extradata></service><service fechaActualizacion="2018-11-23" id="67397"><basicData><language>de</language><name><![CDATA[The Westin Palace]]></name><email>reservations.palacemadrid@westin.com</email><phone>(+34) 91 360 80 00</phone><fax/><title><![CDATA[The Westin Palace]]></title><body><![CDATA[<p><strong>Das 1912 im ehemaligen Palast des Herzogs von Medinaceli errichtete Hotel Palace mit einer Dekoration im Stil der großartigen Pariser Gebäude der Belle-Époque wurde während der Gründerjahre zum größten und luxuriösesten Hotel Europas. Seitdem ist es ein außerordentlicher Zeuge des sozialen und kulturellen Lebens der Stadt sowie politischer, wirtschaftlicher und sozialer Bezugspunkt gewesen.</strong></p><p>Von Anfang an war das Hotel sehr beliebt bei Künstlern, Intellektuellen und Politikern. In seinen Archiven finden sich solch hervorragende Namen wie die des Malers Ignacio de Zuloaga, der aus dem Palace sein Zuhause in Madrid machte; des Schriftstellers Vicente Blasco Ibáñez und dem der geheimnisvollen Mata-Hari, von der gesagt wird, dass ihr Abenteurergeist noch immer durch einige der Zimmer streift. Buster Keaton, Pablo Picasso, Federico García Lorca und Luis Buñuel waren weitere berühmte Gäste.</p><p>Später empfang das Hotel Dolores del Río und die wunderschöne María Félix; Orson Welles mit Rita Hayworth; Hemingway und seine berühmten Dry Martinis, während Stierkämpfer wie Belmonte, El Gallo und Manolete in ihren schimmernden Anzügen das Palace auf dem Weg zur Stierkampfarena Las Ventas verließen. Zu den Erinnerungen gehört auch der junge Salvador Dalí, als dieser noch nicht berühmt war.</p><p>Bei ihrer letzte Renovierung haben die&nbsp;Westin Hotels die neusten Trends im Bereich Technologie und Wellness integriert, ohne dabei in die Umgebung und ihr historisches Erbe einzugreifen.</p>]]></body><web>http://www.esmadrid.com/de/unterkunfte/the-westin-palace</web></basicData><geoData><address>Cortes, 7</address><zipcode>28014</zipcode><locality/><country>Spain</country><latitude>40.415585000000</latitude><longitude>-3.695473000000</longitude><subAdministrativeArea>Madrid</subAdministrativeArea></geoData><multimedia><media type="image"><description/><url>http://www.esmadrid.com/sites/default/files/recursosturisticos/alojamientos/WestinPalace1_1404824226.876.png</url></media><media type="image"><description/><url>http://www.esmadrid.com/sites/default/files/recursosturisticos/alojamientos/palace4.jpg</url></media><media type="image"><description/><url>http://www.esmadrid.com/sites/default/files/recursosturisticos/alojamientos/palace.jpg</url></media><media type="image"><description/><url>http://www.esmadrid.com/sites/default/files/recursosturisticos/alojamientos/palace1.jpg</url></media><media type="image"><description/><url>http://www.esmadrid.com/sites/default/files/recursosturisticos/alojamientos/palace5.jpg</url></media><media type="image"><description/><url>http://www.esmadrid.com/sites/default/files/recursosturisticos/alojamientos/palace2.jpg</url></media><media type="image"><description/><url>http://www.esmadrid.com/sites/default/files/recursosturisticos/alojamientos/palace3.jpg</url></media></multimedia><extradata><item name="idTipo">3</item><item name="Tipo">Unterkunft</item><categorias><categoria><item name="idCategoria">7022</item><item name="Categoria">Hoteles</item><subcategorias><subcategoria><item name="idSubCategoria">7028</item><item name="SubCategoria">5 estrellas Gran Lujo</item></subcategoria></subcategorias></categoria></categorias><item name="Servicios de pago"><![CDATA[]]></item><item name="Horario"><![CDATA[]]></item><fechas/></extradata></service><service fechaActualizacion="2018-11-28" id="67398"><basicData><language>de</language><name><![CDATA[Hotel Urban]]></name><email>urban@derbyhotels.com</email><phone>(+34) 91 787 77 70</phone><fax/><title><![CDATA[Urban]]></title><body><![CDATA[<p><strong>Da, wo Politik, Finanzen, Kultur und Kommerz die Hauptrolle spielen, ganz in der Nähe der Puerta del Sol, befindet sich seit Oktober 2004 das Hotel Urban. Das Gebäude, Werk von Carles Bassò und Mariano Martitegui, fällt wegen seiner avantgardistischen Architektur und seiner wertvollen Sammlung Jahrtausende alter Werke in den Innenräumen auf.</strong></p><p>Mérce Borrel, zusammen mit Jordi für die Innenarchitektur zuständig, betont, dass &bdquo;das Hotel sich anfänglich vom Art Déco inspirieren ließ und das Wesen der Vergangenheit mit der Moderne kombinierte.&ldquo; Die Materialien sind edel (Marmor, Hölzer...) und die in hellen Farben gehaltenen Wände strahlen Helligkeit und Glanz aus. Borrel hebt hervor, dass das raffinierte Beleuchtungssystem, bei dem &bdquo;der Gast über unterschiedliche Szenarien verfügt, die sich je nach Tageszeit und Moment im Zimmer an die Bedürfnisse des Gastes anpassen,&ldquo; zu den innovativsten Elementen gehört.</p><p>Gleichzeitig verwandeln Zimmer, Gänge und Gemeinschaftsbereiche sich in ein einzigartiges Museum mit Werken vom Ende des 19. und Anfang des 20. Jahrhunderts aus Papua-Neuguinea, dem Ägyptischen Museum und orientalischen Kunstwerken. Im Sommer können Sie sich bei Tag und Nacht im Außenpool mit herrlichem Blick auf die Altstadt erfrischen.</p><p>Ein Highlight im Gastronomieangebot des Hotels Urban ist das Restaurant <a href="https://www.esmadrid.com/de/restaurants/cebo"><strong>Cebo</strong></a>, das moderne Küche mit mediterranem Einfluss und Schwerpunkt auf Madrider Gerichte bietet. Ebenso das&nbsp;<strong>Glass Mar</strong>, eine spektakuläre, glasverkleidete Bar, die seit Oktober unter der Leitung von Küchenchef Angel León aus Cádiz steht. Im Mittelpunkt ihres kulinarischen Angebots stehen Tapas und Meeresfrüchte stets mit einem Anklang an die Madrider Küche.</p>]]></body><web>http://www.esmadrid.com/de/unterkunfte/urban</web></basicData><geoData><address>San Jerónimo, 34</address><zipcode>28014</zipcode><locality/><country>Spain</country><latitude>40.416357104600</latitude><longitude>-3.698701858521</longitude><subAdministrativeArea>Madrid</subAdministrativeArea></geoData><multimedia><media type="image"><description/><url>http://www.esmadrid.com/sites/default/files/recursosturisticos/alojamientos/HotelUrban1_1404832322.279.png</url></media><media type="image"><description/><url>http://www.esmadrid.com/sites/default/files/recursosturisticos/alojamientos/HotelUrban4_1404832354.515.png</url></media><media type="image"><description/><url>http://www.esmadrid.com/sites/default/files/recursosturisticos/alojamientos/Urban2_alta.jpg</url></media><media type="image"><description/><url>http://www.esmadrid.com/sites/default/files/recursosturisticos/alojamientos/Urban4_alta.jpg</url></media><media type="image"><description/><url>http://www.esmadrid.com/sites/default/files/recursosturisticos/alojamientos/HotelUrban2_1404832335.659.png</url></media><media type="image"><description/><url>http://www.esmadrid.com/sites/default/files/recursosturisticos/alojamientos/HotelUrban3_1404832346.111.png</url></media></multimedia><extradata><item name="idTipo">3</item><item name="Tipo">Unterkunft</item><categorias><categoria><item name="idCategoria">7022</item><item name="Categoria">Hoteles</item><subcategorias><subcategoria><item name="idSubCategoria">7028</item><item name="SubCategoria">5 estrellas Gran Lujo</item></subcategoria></subcategorias></categoria></categorias><item name="Servicios de pago"><![CDATA[]]></item><item name="Horario"><![CDATA[]]></item><fechas/></extradata></service><service fechaActualizacion="2018-07-09" id="67391"><basicData><language>de</language><name><![CDATA[Meli&aacute; Madrid Princesa]]></name><email>melia.madrid.princesa@melia.com</email><phone>(+34) 91 541 82 00</phone><fax/><title><![CDATA[Meli&aacute; Madrid Princesa]]></title><body><![CDATA[<p><strong><span>Das Hotel Meliá Princesa ist ein Hotel für diejenigen, die das authentische und urige Madrid kennenlernen möchten, denn es liegt mitten im Zentrum der Hauptstadt Spaniens, wenige Schritte von der Plaza de España und der Gran Vía entfernt, sowie für Kauflustige, da es sich im Herzen einer der wichtigsten Geschäftszentren der Stadt befindet.</span></strong></p><p><span>Für einen idealen Tagesabschluss nach einem langen Einkaufs- oder Stadtbummel bietet das Hotel einen Entspannungsplan mit Swimmingpool im Hotel, Spa, Körperpflege, Whirlpool, Sauna, Solarium, türkischem Bad und Massage, Fitnesscenter und ein Freizeitprogramm mit den verschiedensten Aktivitäten. Das 1967 errichtete und 2008 vollständig renovierte Gebäude verbindet die Moderne mit dem traditionellen Luxus großartiger Hotels, denn es ist mit exquisiten Möbeln, Marmorböden, großen Perserteppichen und chinesischen Vasen ausgestattet.</span></p><p><span>Ein Anziehungspunkt ist das Restaurant &quot;UNO by Meliá Madrid Princesa&quot;, spezialisiert auf mediterrane Autorenküche. In der eleganten Bar können Sie eine Kleinigkeit zu sich nehmen.</span></p><p>&nbsp;</p>]]></body><web>http://www.esmadrid.com/de/unterkunfte/melia-madrid-princesa</web></basicData><geoData><address>Calle de la Princesa, 27 Madrid</address><zipcode>28008</zipcode><locality/><country>Spain</country><latitude>40.427555000000</latitude><longitude>-3.714079000000</longitude><subAdministrativeArea>Madrid</subAdministrativeArea></geoData><multimedia><media type="image"><description/><url>http://www.esmadrid.com/sites/default/files/recursosturisticos/alojamientos/melia_madrid_princesa_2.jpg</url></media><media type="image"><description/><url>http://www.esmadrid.com/sites/default/files/recursosturisticos/alojamientos/melia_madrid_princesa_4.jpg</url></media><media type="image"><description/><url>http://www.esmadrid.com/sites/default/files/recursosturisticos/alojamientos/melia_madrid_princesa.jpg</url></media><media type="image"><description/><url>http://www.esmadrid.com/sites/default/files/recursosturisticos/alojamientos/melia_madrid_princesa_3.jpg</url></media></multimedia><extradata><item name="idTipo">3</item><item name="Tipo">Unterkunft</item><categorias><categoria><item name="idCategoria">7022</item><item name="Categoria">Hoteles</item><subcategorias><subcategoria><item name="idSubCategoria">7027</item><item name="SubCategoria">5 estrellas</item></subcategoria></subcategorias></categoria></categorias><item name="Servicios de pago"><![CDATA[]]></item><item name="Horario"><![CDATA[]]></item><fechas/></extradata></service></serviceList>
